{
  "id": "2579082",
  "name": "DebugPanel",
  "font_family": "iconfont",
  "css_prefix_text": "icon-",
  "description": "",
  "glyphs": [
    {
      "icon_id": "8634399",
      "name": "导出",
      "font_class": "daochu",
      "unicode": "e60e",
      "unicode_decimal": 58894
    },
    {
      "icon_id": "2815727",
      "name": "素材",
      "font_class": "sucai",
      "unicode": "e604",
      "unicode_decimal": 58884
    },
    {
      "icon_id": "1304882",
      "name": "开关",
      "font_class": "kaiguan",
      "unicode": "e621",
      "unicode_decimal": 58913
    },
    {
      "icon_id": "1365379",
      "name": "统计",
      "font_class": "tongji",
      "unicode": "e688",
      "unicode_decimal": 59016
    },
    {
      "icon_id": "6326748",
      "name": "重置",
      "font_class": "zhongzhi",
      "unicode": "e627",
      "unicode_decimal": 58919
    },
    {
      "icon_id": "15738459",
      "name": "下拉菜单",
      "font_class": "xialacaidan",
      "unicode": "e600",
      "unicode_decimal": 58880
    },
    {
      "icon_id": "27683676",
      "name": "下拉菜单",
      "font_class": "xialacaidan-copy",
      "unicode": "eb6b",
      "unicode_decimal": 60267
    },
    {
      "icon_id": "20340304",
      "name": "最大值",
      "font_class": "zuidazhi",
      "unicode": "e6db",
      "unicode_decimal": 59099
    },
    {
      "icon_id": "7493450",
      "name": "删除",
      "font_class": "shanchu",
      "unicode": "e653",
      "unicode_decimal": 58963
    },
    {
      "icon_id": "4118038",
      "name": "关闭",
      "font_class": "guanbi",
      "unicode": "eb6a",
      "unicode_decimal": 60266
    },
    {
      "icon_id": "9384062",
      "name": "菜单",
      "font_class": "caidan",
      "unicode": "e608",
      "unicode_decimal": 58888
    },
    {
      "icon_id": "18808316",
      "name": "chrome",
      "font_class": "chrome",
      "unicode": "e882",
      "unicode_decimal": 59522
    },
    {
      "icon_id": "8371995",
      "name": "手机电脑",
      "font_class": "shoujidiannao",
      "unicode": "e62d",
      "unicode_decimal": 58925
    },
    {
      "icon_id": "21523599",
      "name": "退出",
      "font_class": "tuichu",
      "unicode": "e681",
      "unicode_decimal": 59009
    },
    {
      "icon_id": "584125",
      "name": "删除",
      "font_class": "iconfontshanchu6",
      "unicode": "e61d",
      "unicode_decimal": 58909
    },
    {
      "icon_id": "716007",
      "name": "刷新",
      "font_class": "shuaxin",
      "unicode": "e636",
      "unicode_decimal": 58934
    },
    {
      "icon_id": "5772874",
      "name": "复制",
      "font_class": "copy",
      "unicode": "e617",
      "unicode_decimal": 58903
    },
    {
      "icon_id": "1635110",
      "name": "09-隐藏",
      "font_class": "-yincang",
      "unicode": "e60c",
      "unicode_decimal": 58892
    },
    {
      "icon_id": "16589940",
      "name": "置顶",
      "font_class": "56zhiding",
      "unicode": "e630",
      "unicode_decimal": 58928
    },
    {
      "icon_id": "21911500",
      "name": "置顶",
      "font_class": "56zhiding-copy",
      "unicode": "e691",
      "unicode_decimal": 59025
    },
    {
      "icon_id": "21911322",
      "name": "06-左箭头",
      "font_class": "zuojiantou1-copy-copy",
      "unicode": "e68e",
      "unicode_decimal": 59022
    },
    {
      "icon_id": "21911297",
      "name": "20-右箭头",
      "font_class": "youjiantou1-copy",
      "unicode": "e68d",
      "unicode_decimal": 59021
    },
    {
      "icon_id": "632977",
      "name": "查找",
      "font_class": "chazhao",
      "unicode": "e60b",
      "unicode_decimal": 58891
    },
    {
      "icon_id": "15668761",
      "name": "筛 选",
      "font_class": "shaixuan",
      "unicode": "e68b",
      "unicode_decimal": 59019
    }
  ]
}
